LICENSE
MANIFEST.in
README.md
setup.py
django_easy_scraper/__init__.py
django_easy_scraper/admin.py
django_easy_scraper/apps.py
django_easy_scraper/exceptions.py
django_easy_scraper/models.py
django_easy_scraper/scraper.py
django_easy_scraper/setup.py
django_easy_scraper/switch.py
django_easy_scraper/tests.py
django_easy_scraper/views.py
django_easy_scraper.egg-info/PKG-INFO
django_easy_scraper.egg-info/SOURCES.txt
django_easy_scraper.egg-info/dependency_links.txt
django_easy_scraper.egg-info/requires.txt
django_easy_scraper.egg-info/top_level.txt
django_easy_scraper/migrations/__init__.py