Metadata-Version: 2.1
Name: django-easy-scraper
Version: 1.0.6
Summary: Dango app to scrape web page
Home-page: https://github.com/dearopen/django-easy-scraper
Author: dearopen
Author-email: 
License: UNKNOWN
Platform: UNKNOWN
Classifier: Programming Language :: Python :: 3
Classifier: License :: OSI Approved :: MIT License
Classifier: Operating System :: OS Independent
Requires-Python: >=3.6
